mg_crp/__init__.py
mg_crp/crypto_aes.py
mg_crp/main.py
mg_crp-0.0.2.dist-info/WHEEL
mg_crp-0.0.2.dist-info/METADATA
mg_crp-0.0.2.dist-info/RECORD
